answer_rocket/__init__.py
answer_rocket/auth.py
answer_rocket/chat.py
answer_rocket/client.py
answer_rocket/client_config.py
answer_rocket/config.py
answer_rocket/data.py
answer_rocket/email.py
answer_rocket/error.py
answer_rocket/layouts.py
answer_rocket/llm.py
answer_rocket/output.py
answer_rocket/skill.py
answer_rocket/types.py
answer_rocket/graphql/__init__.py
answer_rocket/graphql/client.py
answer_rocket/graphql/schema.py
answer_rocket/graphql/sdk_operations.py
answer_rocket/util/__init__.py
answer_rocket/util/meta_data_frame.py
answerrocket_client-0.2.102.dist-info/METADATA
answerrocket_client-0.2.102.dist-info/WHEEL
answerrocket_client-0.2.102.dist-info/top_level.txt
answerrocket_client-0.2.102.dist-info/RECORD
