Metadata-Version: 2.4
Name: answerrocket-client
Version: 0.2.102
Summary: Python client for interacting with AnswerRocket's skill API
Requires-Python: >=3.10.7
Requires-Dist: sgqlc
Requires-Dist: pandas>=1.5.1
Requires-Dist: typing-extensions
Provides-Extra: test
Requires-Dist: pytest; extra == "test"
